twobodyproblem/__init__.py
twobodyproblem/__main__.py
twobodyproblem/entry.py
twobodyproblem/examples.py
twobodyproblem/options.py
twobodyproblem/preset.py
twobodyproblem/settings.py
twobodyproblem/values.py
twobodyproblem/saved_data/presets.yml
twobodyproblem/ui/entry.ui
twobodyproblem/ui/examples.ui
twobodyproblem/ui/icon.gif
twobodyproblem/ui/settings.ui
twobodyproblem/visualization/__init__.py
twobodyproblem/visualization/__main__.py
twobodyproblem/visualization/body.py
twobodyproblem/visualization/simulation.py
twobodyproblem-2.0.0.dist-info/LICENSE.md
twobodyproblem-2.0.0.dist-info/METADATA
twobodyproblem-2.0.0.dist-info/WHEEL
twobodyproblem-2.0.0.dist-info/top_level.txt
twobodyproblem-2.0.0.dist-info/RECORD
