Metadata-Version: 2.1
Name: twobodyproblem
Version: 2.0.0
Summary: a little simulation for the gravitational two body problem
Home-page: https://github.com/Two-Body-Problem/twobodyproblem-simulation-python
Author: Florian Frauenfelder
Author-email: florian.l.frauenfelder@gmail.com
License: MIT
Keywords: simulation,gravitation,vpython
Platform: UNKNOWN
Classifier: Development Status :: 5 - Production/Stable
Classifier: Intended Audience :: Education
Classifier: Intended Audience :: End Users/Desktop
Classifier: License :: OSI Approved :: MIT License
Classifier: Natural Language :: English
Classifier: Operating System :: OS Independent
Classifier: Programming Language :: Python :: 3 :: Only
Classifier: Programming Language :: Python :: 3.8
Classifier: Programming Language :: Python :: 3.9
Classifier: Topic :: Education
Classifier: Topic :: Scientific/Engineering :: Astronomy
Classifier: Topic :: Scientific/Engineering :: Physics
Requires-Python: >=3.8
Requires-Dist: pyyaml (>=5.4.1)
Requires-Dist: vpython (>=7.6.1)
